pystalmarck-0.1.0.dist-info/METADATA
pystalmarck-0.1.0.dist-info/WHEEL
pystalmarck-0.1.0.dist-info/licenses/LICENSE
pystalmarck/__init__.py
pystalmarck/py.typed
pystalmarck/pystalmarck.cp39-win_amd64.pyd
pystalmarck-0.1.0.dist-info/RECORD
