Metadata-Version: 2.4
Name: pystalmarck
Version: 0.1.0
Classifier: Development Status :: 3 - Alpha
Classifier: Intended Audience :: Developers
Classifier: Intended Audience :: Science/Research
Classifier: License :: OSI Approved :: MIT License
Classifier: Operating System :: POSIX :: Linux
Classifier: Operating System :: MacOS :: MacOS X
Classifier: Operating System :: Microsoft :: Windows
Classifier: Programming Language :: Python :: 3
Classifier: Programming Language :: Python :: 3.8
Classifier: Programming Language :: Python :: 3.9
Classifier: Programming Language :: Python :: 3.10
Classifier: Programming Language :: Python :: 3.11
Classifier: Programming Language :: Python :: 3.12
Classifier: Programming Language :: Rust
Classifier: Topic :: Scientific/Engineering :: Mathematics
Classifier: Topic :: Software Development :: Libraries :: Python Modules
License-File: LICENSE
Summary: Python bindings for StalmarckSAT - A SAT solver based on Stålmarck's method
Keywords: sat,solver,stalmarck,boolean,satisfiability
Author: Liam Davis, Sergei Leonov
License: MIT
Requires-Python: >=3.8
Project-URL: Homepage, https://github.com/Stalmarck-Satisfiability/StalmarckSAT
Project-URL: Repository, https://github.com/Stalmarck-Satisfiability/StalmarckSAT
Project-URL: Issues, https://github.com/Stalmarck-Satisfiability/StalmarckSAT/issues
